django_export_download-0.2.1.dist-info/METADATA
django_export_download-0.2.1.dist-info/RECORD
django_export_download-0.2.1.dist-info/WHEEL
django_export_download-0.2.1.dist-info/top_level.txt
export_download/__init__.py
export_download/templates/export_download_menu.html
export_download/templatetags/__init__.py
export_download/templatetags/export_download.py
export_download/views/__init__.py
