Metadata-Version: 2.1
Name: django-export-download
Version: 0.2.1
Summary: A Django library that adds a ListView Mixin for downloading a list in different file formats
Home-page: https://github.com/soerenbe/django-export-download
Author: Sören Berger
Author-email: soeren.berger@u1337.de
License: GPL-3
Download-URL: https://github.com/soerenbe/django-export-download/
Keywords: django,nagios,icinga
Platform: UNKNOWN
Classifier: Framework :: Django
Classifier: Intended Audience :: Developers
Classifier: License :: OSI Approved :: GNU General Public License v3 (GPLv3)
Requires-Dist: Django (>=1.11)
Requires-Dist: django-import-export (>=1.0)
